tanxconnector/__init__.py
tanxconnector/client.py
tanxconnector/constants.py
tanxconnector/exception.py
tanxconnector/session.py
tanxconnector/typings.py
tanxconnector/utils.py
tanxconnector/wsclient.py
tanxconnector/bin/__init__.py
tanxconnector/bin/blockchain_utils.py
tanxconnector/bin/cross_network_deposit_abi.json
tanxconnector/bin/erc20_abi.json
tanxconnector/bin/math_utils.py
tanxconnector/bin/pedersen_params.json
tanxconnector/bin/signature.py
tanxconnector/bin/starkex_abi_main.json
tanxconnector/bin/starkex_abi_test.json
tanx_connector-2.1.0.dist-info/LICENSE
tanx_connector-2.1.0.dist-info/METADATA
tanx_connector-2.1.0.dist-info/WHEEL
tanx_connector-2.1.0.dist-info/top_level.txt
tanx_connector-2.1.0.dist-info/RECORD
