Metadata-Version: 2.1
Name: tanx-connector
Version: 2.1.0
Summary: The official Python connector for Tanx's API
Author: tanX
License: MIT License
Project-URL: Homepage, https://github.com/tanx-libs/tanx-connector-python
Project-URL: Issues, https://github.com/tanx-libs/tanx-connector-python/issues
Keywords: tanx,connector,finance,api,wrapper,python
Classifier: License :: OSI Approved :: MIT License
Classifier: Programming Language :: Python :: 3.8
Classifier: Programming Language :: Python :: 3.9
Classifier: Programming Language :: Python :: 3.10
Classifier: Programming Language :: Python :: 3.11
Requires-Python: >=3.8
License-File: LICENSE
Requires-Dist: requests
Requires-Dist: web3
Requires-Dist: ecdsa
Requires-Dist: websockets
Requires-Dist: sympy
Requires-Dist: typing-extensions
Provides-Extra: dev
Requires-Dist: eth-tester ; extra == 'dev'
Requires-Dist: pytest ; extra == 'dev'
Requires-Dist: pytest-mock ; extra == 'dev'
Requires-Dist: responses ; extra == 'dev'
Requires-Dist: pip-tools ; extra == 'dev'
Requires-Dist: bumpver ; extra == 'dev'
Requires-Dist: build ; extra == 'dev'
Requires-Dist: twine ; extra == 'dev'
Requires-Dist: python-dotenv ; extra == 'dev'
